pycomunefirenze/__init__.py
pycomunefirenze/cdf.py
pycomunefirenze/working_dir.py
pycomunefirenze-0.6.2.dist-info/METADATA
pycomunefirenze-0.6.2.dist-info/WHEEL
pycomunefirenze-0.6.2.dist-info/top_level.txt
pycomunefirenze-0.6.2.dist-info/RECORD
