Metadata-Version: 2.1
Name: pycomunefirenze
Version: 0.6.2
Summary: UNKNOWN
Home-page: UNKNOWN
Author: Ubaldo Puocci
Author-email: ubaldo.puocci@comune.fi.it
License: UNKNOWN
Platform: UNKNOWN
Requires-Dist: requests
Requires-Dist: psycopg2
Requires-Dist: redmail
